{
  "scene_dimensions": [
    256,
    256
  ],
  "bodies": [
    {
      "position": [
        128.0,
        258.5
      ],
      "bodyType": 0,
      "angle": 0.0,
      "color": 6,
      "shapeType": 0,
      "diameter": 256.0488234692751,
      "vertices": [
        [
          128.0,
          2.5
        ],
        [
          -128.0,
          2.5
        ],
        [
          -128.0,
          -2.5
        ],
        [
          128.0,
          -2.5
        ]
      ]
    },
    {
      "position": [
        -2.5,
        128.0
      ],
      "bodyType": 0,
      "angle": 0.0,
      "color": 6,
      "shapeType": 0,
      "diameter": 256.0488234692751,
      "vertices": [
        [
          2.5,
          128.0
        ],
        [
          -2.5,
          128.0
        ],
        [
          -2.5,
          -128.0
        ],
        [
          2.5,
          -128.0
        ]
      ]
    },
    {
      "position": [
        128.0,
        -2.5
      ],
      "bodyType": 0,
      "angle": 0.0,
      "color": 6,
      "shapeType": 0,
      "diameter": 256.0488234692751,
      "vertices": [
        [
          128.0,
          2.5
        ],
        [
          -128.0,
          2.5
        ],
        [
          -128.0,
          -2.5
        ],
        [
          128.0,
          -2.5
        ]
      ]
    },
    {
      "position": [
        258.5,
        128.0
      ],
      "bodyType": 0,
      "angle": 0.0,
      "color": 6,
      "shapeType": 0,
      "diameter": 256.0488234692751,
      "vertices": [
        [
          2.5,
          128.0
        ],
        [
          -2.5,
          128.0
        ],
        [
          -2.5,
          -128.0
        ],
        [
          2.5,
          -128.0
        ]
      ]
    },
    {
      "position": [
        70.49948444314161,
        25.599999999999994
      ],
      "bodyType": 1,
      "angle": 0.0,
      "color": 2,
      "shapeType": 1,
      "diameter": 25.0,
      "radius": 12.5
    },
    {
      "position": [
        0.0,
        88.1
      ],
      "bodyType": 0,
      "angle": 0.0,
      "color": 6,
      "shapeType": 1,
      "diameter": 11.0,
      "radius": 5.5
    },
    {
      "position": [
        35.97127483735771,
        79.37883678360166
      ],
      "bodyType": 0,
      "angle": 0.0,
      "color": 6,
      "shapeType": 1,
      "diameter": 11.0,
      "radius": 5.5
    },
    {
      "position": [
        57.36935567592515,
        68.81319898504006
      ],
      "bodyType": 0,
      "angle": 0.0,
      "color": 6,
      "shapeType": 1,
      "diameter": 11.0,
      "radius": 5.5
    },
    {
      "position": [
        89.14892297977624,
        77.17205058752052
      ],
      "bodyType": 0,
      "angle": 0.0,
      "color": 6,
      "shapeType": 1,
      "diameter": 11.0,
      "radius": 5.5
    },
    {
      "position": [
        126.83625918981743,
        77.74565931011733
      ],
      "bodyType": 0,
      "angle": 0.0,
      "color": 6,
      "shapeType": 1,
      "diameter": 11.0,
      "radius": 5.5
    },
    {
      "position": [
        159.16768405571656,
        68.38829943599774
      ],
      "bodyType": 0,
      "angle": 0.0,
      "color": 6,
      "shapeType": 1,
      "diameter": 11.0,
      "radius": 5.5
    },
    {
      "position": [
        256.0,
        135.53333333333333
      ],
      "bodyType": 0,
      "angle": 0.0,
      "color": 6,
      "shapeType": 1,
      "diameter": 11.0,
      "radius": 5.5
    },
    {
      "position": [
        214.9432178470245,
        129.29925406497318
      ],
      "bodyType": 0,
      "angle": 0.0,
      "color": 6,
      "shapeType": 1,
      "diameter": 11.0,
      "radius": 5.5
    },
    {
      "position": [
        175.2516229051368,
        118.67217076068533
      ],
      "bodyType": 0,
      "angle": 0.0,
      "color": 6,
      "shapeType": 1,
      "diameter": 11.0,
      "radius": 5.5
    },
    {
      "position": [
        145.9558508621428,
        118.77199107264241
      ],
      "bodyType": 0,
      "angle": 0.0,
      "color": 6,
      "shapeType": 1,
      "diameter": 11.0,
      "radius": 5.5
    },
    {
      "position": [
        103.73012097264777,
        112.66541745662036
      ],
      "bodyType": 0,
      "angle": 0.0,
      "color": 6,
      "shapeType": 1,
      "diameter": 11.0,
      "radius": 5.5
    },
    {
      "position": [
        0.0,
        182.96666666666667
      ],
      "bodyType": 0,
      "angle": 0.0,
      "color": 6,
      "shapeType": 1,
      "diameter": 11.0,
      "radius": 5.5
    },
    {
      "position": [
        28.62800101056148,
        181.24439257753772
      ],
      "bodyType": 0,
      "angle": 0.0,
      "color": 6,
      "shapeType": 1,
      "diameter": 11.0,
      "radius": 5.5
    },
    {
      "position": [
        44.8847906677496,
        176.18823768518786
      ],
      "bodyType": 0,
      "angle": 0.0,
      "color": 6,
      "shapeType": 1,
      "diameter": 11.0,
      "radius": 5.5
    },
    {
      "position": [
        68.15049366341648,
        176.4761320690942
      ],
      "bodyType": 0,
      "angle": 0.0,
      "color": 6,
      "shapeType": 1,
      "diameter": 11.0,
      "radius": 5.5
    },
    {
      "position": [
        92.55500662145926,
        176.67903685802628
      ],
      "bodyType": 0,
      "angle": 0.0,
      "color": 6,
      "shapeType": 1,
      "diameter": 11.0,
      "radius": 5.5
    },
    {
      "position": [
        116.51201471473334,
        173.84172099157757
      ],
      "bodyType": 0,
      "angle": 0.0,
      "color": 6,
      "shapeType": 1,
      "diameter": 11.0,
      "radius": 5.5
    },
    {
      "position": [
        256.0,
        230.4
      ],
      "bodyType": 0,
      "angle": 0.0,
      "color": 6,
      "shapeType": 1,
      "diameter": 11.0,
      "radius": 5.5
    },
    {
      "position": [
        214.69811992285764,
        225.7406949805993
      ],
      "bodyType": 0,
      "angle": 0.0,
      "color": 6,
      "shapeType": 1,
      "diameter": 11.0,
      "radius": 5.5
    },
    {
      "position": [
        183.3925987664614,
        214.96404278960762
      ],
      "bodyType": 0,
      "angle": 0.0,
      "color": 6,
      "shapeType": 1,
      "diameter": 11.0,
      "radius": 5.5
    },
    {
      "position": [
        140.79178125773336,
        208.46909188853834
      ],
      "bodyType": 0,
      "angle": 0.0,
      "color": 6,
      "shapeType": 1,
      "diameter": 11.0,
      "radius": 5.5
    },
    {
      "position": [
        123.06461607330655,
        207.99530001651127
      ],
      "bodyType": 0,
      "angle": 0.0,
      "color": 6,
      "shapeType": 1,
      "diameter": 11.0,
      "radius": 5.5
    },
    {
      "position": [
        92.05554505104877,
        212.0605202983657
      ],
      "bodyType": 0,
      "angle": 0.0,
      "color": 6,
      "shapeType": 1,
      "diameter": 11.0,
      "radius": 5.5
    },
    {
      "position": [
        61.33371487820986,
        216.6033489810555
      ],
      "bodyType": 0,
      "angle": 0.0,
      "color": 6,
      "shapeType": 1,
      "diameter": 11.0,
      "radius": 5.5
    },
    {
      "position": [
        40.440225964204274,
        216.93392531708878
      ],
      "bodyType": 0,
      "angle": 0.0,
      "color": 6,
      "shapeType": 1,
      "diameter": 11.0,
      "radius": 5.5
    },
    {
      "position": [
        128.0,
        253.44
      ],
      "bodyType": 0,
      "angle": 0.0,
      "color": 4,
      "shapeType": 2,
      "diameter": 256.0511948810237,
      "vertices": [
        [
          128.0,
          2.56
        ],
        [
          -128.0,
          2.56
        ],
        [
          -128.0,
          -2.56
        ],
        [
          128.0,
          -2.56
        ]
      ]
    }
  ],
  "relationship": {
    "bodyId1": 4,
    "bodyId2": 30,
    "relationships": [
      0
    ]
  },
  "metadata": {
    "description": "Make sure the green ball is touching the purple bar.",
    "tier": 0
  }
}