{
  "scene_dimensions": [
    256,
    256
  ],
  "bodies": [
    {
      "position": [
        128.0,
        258.5
      ],
      "bodyType": 0,
      "angle": 0.0,
      "color": 6,
      "shapeType": 0,
      "diameter": 256.0488234692751,
      "vertices": [
        [
          128.0,
          2.5
        ],
        [
          -128.0,
          2.5
        ],
        [
          -128.0,
          -2.5
        ],
        [
          128.0,
          -2.5
        ]
      ]
    },
    {
      "position": [
        -2.5,
        128.0
      ],
      "bodyType": 0,
      "angle": 0.0,
      "color": 6,
      "shapeType": 0,
      "diameter": 256.0488234692751,
      "vertices": [
        [
          2.5,
          128.0
        ],
        [
          -2.5,
          128.0
        ],
        [
          -2.5,
          -128.0
        ],
        [
          2.5,
          -128.0
        ]
      ]
    },
    {
      "position": [
        128.0,
        -2.5
      ],
      "bodyType": 0,
      "angle": 0.0,
      "color": 6,
      "shapeType": 0,
      "diameter": 256.0488234692751,
      "vertices": [
        [
          128.0,
          2.5
        ],
        [
          -128.0,
          2.5
        ],
        [
          -128.0,
          -2.5
        ],
        [
          128.0,
          -2.5
        ]
      ]
    },
    {
      "position": [
        258.5,
        128.0
      ],
      "bodyType": 0,
      "angle": 0.0,
      "color": 6,
      "shapeType": 0,
      "diameter": 256.0488234692751,
      "vertices": [
        [
          2.5,
          128.0
        ],
        [
          -2.5,
          128.0
        ],
        [
          -2.5,
          -128.0
        ],
        [
          2.5,
          -128.0
        ]
      ]
    },
    {
      "position": [
        103.21947946931658,
        17.919999999999987
      ],
      "bodyType": 1,
      "angle": 0.0,
      "color": 2,
      "shapeType": 1,
      "diameter": 17.0,
      "radius": 8.5
    },
    {
      "position": [
        103.21947946931658,
        57.903153018261634
      ],
      "bodyType": 0,
      "angle": 0.0,
      "color": 6,
      "shapeType": 2,
      "diameter": 74.84991774887317,
      "vertices": [
        [
          37.33729967141799,
          2.56
        ],
        [
          -37.33729967141799,
          2.56
        ],
        [
          -37.33729967141799,
          -2.56
        ],
        [
          37.33729967141799,
          -2.56
        ]
      ]
    },
    {
      "position": [
        139.27677914073456,
        55.903153018261634
      ],
      "bodyType": 0,
      "angle": 0.0,
      "color": 6,
      "shapeType": 2,
      "diameter": 5.724334022399462,
      "vertices": [
        [
          1.28,
          2.56
        ],
        [
          -1.28,
          2.56
        ],
        [
          -1.28,
          -2.56
        ],
        [
          1.28,
          -2.56
        ]
      ]
    },
    {
      "position": [
        67.1621797978986,
        55.903153018261634
      ],
      "bodyType": 0,
      "angle": 0.0,
      "color": 6,
      "shapeType": 2,
      "diameter": 5.724334022399462,
      "vertices": [
        [
          1.28,
          2.56
        ],
        [
          -1.28,
          2.56
        ],
        [
          -1.28,
          -2.56
        ],
        [
          1.28,
          -2.56
        ]
      ]
    },
    {
      "position": [
        140.55677914073456,
        91.66534690440506
      ],
      "bodyType": 0,
      "angle": 0.0,
      "color": 6,
      "shapeType": 2,
      "diameter": 62.1935136479929,
      "vertices": [
        [
          30.991203348220765,
          2.56
        ],
        [
          -30.991203348220765,
          2.56
        ],
        [
          -30.991203348220765,
          -2.56
        ],
        [
          30.991203348220765,
          -2.56
        ]
      ]
    },
    {
      "position": [
        170.2679824889553,
        89.66534690440506
      ],
      "bodyType": 0,
      "angle": 0.0,
      "color": 6,
      "shapeType": 2,
      "diameter": 5.724334022399462,
      "vertices": [
        [
          1.28,
          2.56
        ],
        [
          -1.28,
          2.56
        ],
        [
          -1.28,
          -2.56
        ],
        [
          1.28,
          -2.56
        ]
      ]
    },
    {
      "position": [
        110.8455757925138,
        89.66534690440506
      ],
      "bodyType": 0,
      "angle": 0.0,
      "color": 6,
      "shapeType": 2,
      "diameter": 5.724334022399462,
      "vertices": [
        [
          1.28,
          2.56
        ],
        [
          -1.28,
          2.56
        ],
        [
          -1.28,
          -2.56
        ],
        [
          1.28,
          -2.56
        ]
      ]
    },
    {
      "position": [
        65.8821797978986,
        121.44542777652342
      ],
      "bodyType": 0,
      "angle": 0.0,
      "color": 6,
      "shapeType": 2,
      "diameter": 43.119600976613874,
      "vertices": [
        [
          21.40727439669983,
          2.56
        ],
        [
          -21.40727439669983,
          2.56
        ],
        [
          -21.40727439669983,
          -2.56
        ],
        [
          21.40727439669983,
          -2.56
        ]
      ]
    },
    {
      "position": [
        86.00945419459843,
        119.44542777652342
      ],
      "bodyType": 0,
      "angle": 0.0,
      "color": 6,
      "shapeType": 2,
      "diameter": 5.724334022399462,
      "vertices": [
        [
          1.28,
          2.56
        ],
        [
          -1.28,
          2.56
        ],
        [
          -1.28,
          -2.56
        ],
        [
          1.28,
          -2.56
        ]
      ]
    },
    {
      "position": [
        45.75490540119877,
        119.44542777652342
      ],
      "bodyType": 0,
      "angle": 0.0,
      "color": 6,
      "shapeType": 2,
      "diameter": 5.724334022399462,
      "vertices": [
        [
          1.28,
          2.56
        ],
        [
          -1.28,
          2.56
        ],
        [
          -1.28,
          -2.56
        ],
        [
          1.28,
          -2.56
        ]
      ]
    },
    {
      "position": [
        109.5655757925138,
        149.220313481332
      ],
      "bodyType": 0,
      "angle": 0.0,
      "color": 6,
      "shapeType": 2,
      "diameter": 77.53040620231482,
      "vertices": [
        [
          38.680581322854806,
          2.56
        ],
        [
          -38.680581322854806,
          2.56
        ],
        [
          -38.680581322854806,
          -2.56
        ],
        [
          38.680581322854806,
          -2.56
        ]
      ]
    },
    {
      "position": [
        146.9661571153686,
        147.220313481332
      ],
      "bodyType": 0,
      "angle": 0.0,
      "color": 6,
      "shapeType": 2,
      "diameter": 5.724334022399462,
      "vertices": [
        [
          1.28,
          2.56
        ],
        [
          -1.28,
          2.56
        ],
        [
          -1.28,
          -2.56
        ],
        [
          1.28,
          -2.56
        ]
      ]
    },
    {
      "position": [
        72.16499446965899,
        147.220313481332
      ],
      "bodyType": 0,
      "angle": 0.0,
      "color": 6,
      "shapeType": 2,
      "diameter": 5.724334022399462,
      "vertices": [
        [
          1.28,
          2.56
        ],
        [
          -1.28,
          2.56
        ],
        [
          -1.28,
          -2.56
        ],
        [
          1.28,
          -2.56
        ]
      ]
    },
    {
      "position": [
        171.5479824889553,
        183.13824125657823
      ],
      "bodyType": 0,
      "angle": 0.0,
      "color": 6,
      "shapeType": 2,
      "diameter": 81.5808411583645,
      "vertices": [
        [
          40.71000873282362,
          2.56
        ],
        [
          -40.71000873282362,
          2.56
        ],
        [
          -40.71000873282362,
          -2.56
        ],
        [
          40.71000873282362,
          -2.56
        ]
      ]
    },
    {
      "position": [
        210.97799122177892,
        181.13824125657823
      ],
      "bodyType": 0,
      "angle": 0.0,
      "color": 6,
      "shapeType": 2,
      "diameter": 5.724334022399462,
      "vertices": [
        [
          1.28,
          2.56
        ],
        [
          -1.28,
          2.56
        ],
        [
          -1.28,
          -2.56
        ],
        [
          1.28,
          -2.56
        ]
      ]
    },
    {
      "position": [
        132.1179737561317,
        181.13824125657823
      ],
      "bodyType": 0,
      "angle": 0.0,
      "color": 6,
      "shapeType": 2,
      "diameter": 5.724334022399462,
      "vertices": [
        [
          1.28,
          2.56
        ],
        [
          -1.28,
          2.56
        ],
        [
          -1.28,
          -2.56
        ],
        [
          1.28,
          -2.56
        ]
      ]
    },
    {
      "position": [
        44.47490540119877,
        223.6131236370519
      ],
      "bodyType": 0,
      "angle": 0.0,
      "color": 6,
      "shapeType": 2,
      "diameter": 83.41654385041548,
      "vertices": [
        [
          41.62963303930353,
          2.56
        ],
        [
          -41.62963303930353,
          2.56
        ],
        [
          -41.62963303930353,
          -2.56
        ],
        [
          41.62963303930353,
          -2.56
        ]
      ]
    },
    {
      "position": [
        84.8245384405023,
        221.6131236370519
      ],
      "bodyType": 0,
      "angle": 0.0,
      "color": 6,
      "shapeType": 2,
      "diameter": 5.724334022399462,
      "vertices": [
        [
          1.28,
          2.56
        ],
        [
          -1.28,
          2.56
        ],
        [
          -1.28,
          -2.56
        ],
        [
          1.28,
          -2.56
        ]
      ]
    },
    {
      "position": [
        4.125272361895241,
        221.6131236370519
      ],
      "bodyType": 0,
      "angle": 0.0,
      "color": 6,
      "shapeType": 2,
      "diameter": 5.724334022399462,
      "vertices": [
        [
          1.28,
          2.56
        ],
        [
          -1.28,
          2.56
        ],
        [
          -1.28,
          -2.56
        ],
        [
          1.28,
          -2.56
        ]
      ]
    },
    {
      "position": [
        19.35284819266173,
        252.1448471410837
      ],
      "bodyType": 0,
      "angle": 0.17453292519943295,
      "color": 6,
      "shapeType": 2,
      "diameter": 38.73982963307918,
      "vertices": [
        [
          19.2,
          2.56
        ],
        [
          -19.2,
          2.56
        ],
        [
          -19.2,
          -2.56
        ],
        [
          19.2,
          -2.56
        ]
      ]
    },
    {
      "position": [
        236.64715180733828,
        252.1448471410837
      ],
      "bodyType": 0,
      "angle": -0.17453292519943295,
      "color": 6,
      "shapeType": 2,
      "diameter": 38.73982963307918,
      "vertices": [
        [
          19.2,
          2.56
        ],
        [
          -19.2,
          2.56
        ],
        [
          -19.2,
          -2.56
        ],
        [
          19.2,
          -2.56
        ]
      ]
    },
    {
      "position": [
        128.0,
        253.44
      ],
      "bodyType": 0,
      "angle": 0.0,
      "color": 4,
      "shapeType": 2,
      "diameter": 178.66198541413377,
      "vertices": [
        [
          89.29430361467655,
          2.56
        ],
        [
          -89.29430361467655,
          2.56
        ],
        [
          -89.29430361467655,
          -2.56
        ],
        [
          89.29430361467655,
          -2.56
        ]
      ]
    }
  ],
  "relationship": {
    "bodyId1": 4,
    "bodyId2": 25,
    "relationships": [
      0
    ]
  },
  "metadata": {
    "description": "Make sure the green ball is touching the purple bar.",
    "tier": 1
  }
}