{
  "scene_dimensions": [
    256,
    256
  ],
  "bodies": [
    {
      "position": [
        128.0,
        258.5
      ],
      "bodyType": 0,
      "angle": 0.0,
      "color": 6,
      "shapeType": 0,
      "diameter": 256.0488234692751,
      "vertices": [
        [
          128.0,
          2.5
        ],
        [
          -128.0,
          2.5
        ],
        [
          -128.0,
          -2.5
        ],
        [
          128.0,
          -2.5
        ]
      ]
    },
    {
      "position": [
        -2.5,
        128.0
      ],
      "bodyType": 0,
      "angle": 0.0,
      "color": 6,
      "shapeType": 0,
      "diameter": 256.0488234692751,
      "vertices": [
        [
          2.5,
          128.0
        ],
        [
          -2.5,
          128.0
        ],
        [
          -2.5,
          -128.0
        ],
        [
          2.5,
          -128.0
        ]
      ]
    },
    {
      "position": [
        128.0,
        -2.5
      ],
      "bodyType": 0,
      "angle": 0.0,
      "color": 6,
      "shapeType": 0,
      "diameter": 256.0488234692751,
      "vertices": [
        [
          128.0,
          2.5
        ],
        [
          -128.0,
          2.5
        ],
        [
          -128.0,
          -2.5
        ],
        [
          128.0,
          -2.5
        ]
      ]
    },
    {
      "position": [
        258.5,
        128.0
      ],
      "bodyType": 0,
      "angle": 0.0,
      "color": 6,
      "shapeType": 0,
      "diameter": 256.0488234692751,
      "vertices": [
        [
          2.5,
          128.0
        ],
        [
          -2.5,
          128.0
        ],
        [
          -2.5,
          -128.0
        ],
        [
          2.5,
          -128.0
        ]
      ]
    },
    {
      "position": [
        117.02673292257259,
        17.919999999999987
      ],
      "bodyType": 1,
      "angle": 0.0,
      "color": 2,
      "shapeType": 1,
      "diameter": 17.0,
      "radius": 8.5
    },
    {
      "position": [
        117.02673292257259,
        57.107672993637294
      ],
      "bodyType": 0,
      "angle": 0.0,
      "color": 6,
      "shapeType": 2,
      "diameter": 53.66622991383164,
      "vertices": [
        [
          26.710718041472784,
          2.56
        ],
        [
          -26.710718041472784,
          2.56
        ],
        [
          -26.710718041472784,
          -2.56
        ],
        [
          26.710718041472784,
          -2.56
        ]
      ]
    },
    {
      "position": [
        142.45745096404536,
        55.107672993637294
      ],
      "bodyType": 0,
      "angle": 0.0,
      "color": 6,
      "shapeType": 2,
      "diameter": 5.724334022399462,
      "vertices": [
        [
          1.28,
          2.56
        ],
        [
          -1.28,
          2.56
        ],
        [
          -1.28,
          -2.56
        ],
        [
          1.28,
          -2.56
        ]
      ]
    },
    {
      "position": [
        91.5960148810998,
        55.107672993637294
      ],
      "bodyType": 0,
      "angle": 0.0,
      "color": 6,
      "shapeType": 2,
      "diameter": 5.724334022399462,
      "vertices": [
        [
          1.28,
          2.56
        ],
        [
          -1.28,
          2.56
        ],
        [
          -1.28,
          -2.56
        ],
        [
          1.28,
          -2.56
        ]
      ]
    },
    {
      "position": [
        143.73745096404537,
        85.78812658352959
      ],
      "bodyType": 0,
      "angle": 0.0,
      "color": 6,
      "shapeType": 2,
      "diameter": 73.3298304003958,
      "vertices": [
        [
          36.57543446956855,
          2.56
        ],
        [
          -36.57543446956855,
          2.56
        ],
        [
          -36.57543446956855,
          -2.56
        ],
        [
          36.57543446956855,
          -2.56
        ]
      ]
    },
    {
      "position": [
        179.03288543361393,
        83.78812658352959
      ],
      "bodyType": 0,
      "angle": 0.0,
      "color": 6,
      "shapeType": 2,
      "diameter": 5.724334022399462,
      "vertices": [
        [
          1.28,
          2.56
        ],
        [
          -1.28,
          2.56
        ],
        [
          -1.28,
          -2.56
        ],
        [
          1.28,
          -2.56
        ]
      ]
    },
    {
      "position": [
        108.44201649447682,
        83.78812658352959
      ],
      "bodyType": 0,
      "angle": 0.0,
      "color": 6,
      "shapeType": 2,
      "diameter": 5.724334022399462,
      "vertices": [
        [
          1.28,
          2.56
        ],
        [
          -1.28,
          2.56
        ],
        [
          -1.28,
          -2.56
        ],
        [
          1.28,
          -2.56
        ]
      ]
    },
    {
      "position": [
        90.3160148810998,
        165.63767835948823
      ],
      "bodyType": 0,
      "angle": 0.0,
      "color": 6,
      "shapeType": 2,
      "diameter": 59.57260686861146,
      "vertices": [
        [
          29.676089234946932,
          2.56
        ],
        [
          -29.676089234946932,
          2.56
        ],
        [
          -29.676089234946932,
          -2.56
        ],
        [
          29.676089234946932,
          -2.56
        ]
      ]
    },
    {
      "position": [
        118.71210411604673,
        163.63767835948823
      ],
      "bodyType": 0,
      "angle": 0.0,
      "color": 6,
      "shapeType": 2,
      "diameter": 5.724334022399462,
      "vertices": [
        [
          1.28,
          2.56
        ],
        [
          -1.28,
          2.56
        ],
        [
          -1.28,
          -2.56
        ],
        [
          1.28,
          -2.56
        ]
      ]
    },
    {
      "position": [
        61.919925646152876,
        163.63767835948823
      ],
      "bodyType": 0,
      "angle": 0.0,
      "color": 6,
      "shapeType": 2,
      "diameter": 5.724334022399462,
      "vertices": [
        [
          1.28,
          2.56
        ],
        [
          -1.28,
          2.56
        ],
        [
          -1.28,
          -2.56
        ],
        [
          1.28,
          -2.56
        ]
      ]
    },
    {
      "position": [
        107.16201649447682,
        188.45686799997213
      ],
      "bodyType": 0,
      "angle": 0.0,
      "color": 6,
      "shapeType": 2,
      "diameter": 64.7753634941337,
      "vertices": [
        [
          32.286348956630064,
          2.56
        ],
        [
          -32.286348956630064,
          2.56
        ],
        [
          -32.286348956630064,
          -2.56
        ],
        [
          32.286348956630064,
          -2.56
        ]
      ]
    },
    {
      "position": [
        138.1683654511069,
        186.45686799997213
      ],
      "bodyType": 0,
      "angle": 0.0,
      "color": 6,
      "shapeType": 2,
      "diameter": 5.724334022399462,
      "vertices": [
        [
          1.28,
          2.56
        ],
        [
          -1.28,
          2.56
        ],
        [
          -1.28,
          -2.56
        ],
        [
          1.28,
          -2.56
        ]
      ]
    },
    {
      "position": [
        76.15566753784675,
        186.45686799997213
      ],
      "bodyType": 0,
      "angle": 0.0,
      "color": 6,
      "shapeType": 2,
      "diameter": 5.724334022399462,
      "vertices": [
        [
          1.28,
          2.56
        ],
        [
          -1.28,
          2.56
        ],
        [
          -1.28,
          -2.56
        ],
        [
          1.28,
          -2.56
        ]
      ]
    },
    {
      "position": [
        19.35284819266173,
        252.1448471410837
      ],
      "bodyType": 0,
      "angle": 0.17453292519943295,
      "color": 6,
      "shapeType": 2,
      "diameter": 38.73982963307918,
      "vertices": [
        [
          19.2,
          2.56
        ],
        [
          -19.2,
          2.56
        ],
        [
          -19.2,
          -2.56
        ],
        [
          19.2,
          -2.56
        ]
      ]
    },
    {
      "position": [
        236.64715180733828,
        252.1448471410837
      ],
      "bodyType": 0,
      "angle": -0.17453292519943295,
      "color": 6,
      "shapeType": 2,
      "diameter": 38.73982963307918,
      "vertices": [
        [
          19.2,
          2.56
        ],
        [
          -19.2,
          2.56
        ],
        [
          -19.2,
          -2.56
        ],
        [
          19.2,
          -2.56
        ]
      ]
    },
    {
      "position": [
        128.0,
        253.44
      ],
      "bodyType": 0,
      "angle": 0.0,
      "color": 4,
      "shapeType": 2,
      "diameter": 178.66198541413377,
      "vertices": [
        [
          89.29430361467655,
          2.56
        ],
        [
          -89.29430361467655,
          2.56
        ],
        [
          -89.29430361467655,
          -2.56
        ],
        [
          89.29430361467655,
          -2.56
        ]
      ]
    }
  ],
  "relationship": {
    "bodyId1": 4,
    "bodyId2": 19,
    "relationships": [
      0
    ]
  },
  "metadata": {
    "description": "Make sure the green ball is touching the purple bar.",
    "tier": 1
  }
}