{
  "scene_dimensions": [
    256,
    256
  ],
  "bodies": [
    {
      "position": [
        128.0,
        258.5
      ],
      "bodyType": 0,
      "angle": 0.0,
      "color": 6,
      "shapeType": 0,
      "diameter": 256.0488234692751,
      "vertices": [
        [
          128.0,
          2.5
        ],
        [
          -128.0,
          2.5
        ],
        [
          -128.0,
          -2.5
        ],
        [
          128.0,
          -2.5
        ]
      ]
    },
    {
      "position": [
        -2.5,
        128.0
      ],
      "bodyType": 0,
      "angle": 0.0,
      "color": 6,
      "shapeType": 0,
      "diameter": 256.0488234692751,
      "vertices": [
        [
          2.5,
          128.0
        ],
        [
          -2.5,
          128.0
        ],
        [
          -2.5,
          -128.0
        ],
        [
          2.5,
          -128.0
        ]
      ]
    },
    {
      "position": [
        128.0,
        -2.5
      ],
      "bodyType": 0,
      "angle": 0.0,
      "color": 6,
      "shapeType": 0,
      "diameter": 256.0488234692751,
      "vertices": [
        [
          128.0,
          2.5
        ],
        [
          -128.0,
          2.5
        ],
        [
          -128.0,
          -2.5
        ],
        [
          128.0,
          -2.5
        ]
      ]
    },
    {
      "position": [
        258.5,
        128.0
      ],
      "bodyType": 0,
      "angle": 0.0,
      "color": 6,
      "shapeType": 0,
      "diameter": 256.0488234692751,
      "vertices": [
        [
          2.5,
          128.0
        ],
        [
          -2.5,
          128.0
        ],
        [
          -2.5,
          -128.0
        ],
        [
          2.5,
          -128.0
        ]
      ]
    },
    {
      "position": [
        150.29722332719646,
        235.5902325923965
      ],
      "bodyType": 0,
      "angle": 0.0,
      "color": 6,
      "shapeType": 0,
      "diameter": 41.75367131160028,
      "vertices": [
        [
          4.391316586948989,
          -20.409767407603518
        ],
        [
          4.391316586948989,
          20.40976740760351
        ],
        [
          -4.391316586949017,
          20.40976740760351
        ],
        [
          -4.391316586949017,
          -20.409767407603518
        ]
      ]
    },
    {
      "position": [
        17.51006906814888,
        235.5902325923965
      ],
      "bodyType": 0,
      "angle": 0.0,
      "color": 6,
      "shapeType": 0,
      "diameter": 41.041915975918364,
      "vertices": [
        [
          2.1333333333333293,
          -20.409767407603518
        ],
        [
          2.1333333333333293,
          20.40976740760351
        ],
        [
          -2.1333333333333364,
          20.40976740760351
        ],
        [
          -2.1333333333333364,
          -20.409767407603518
        ]
      ]
    },
    {
      "position": [
        225.15265934397019,
        245.33333333333334
      ],
      "bodyType": 0,
      "angle": 0.0,
      "color": 4,
      "shapeType": 0,
      "diameter": 53.332291937996274,
      "vertices": [
        [
          26.580673989363135,
          -2.1333333333333346
        ],
        [
          26.580673989363135,
          2.133333333333333
        ],
        [
          -26.580673989363078,
          2.133333333333333
        ],
        [
          -26.580673989363078,
          -2.1333333333333346
        ]
      ]
    },
    {
      "position": [
        225.15265934397024,
        237.01783789216583
      ],
      "bodyType": 0,
      "angle": 0.0,
      "color": 6,
      "shapeType": 0,
      "diameter": 54.58965490524793,
      "vertices": [
        [
          -30.847340656029814,
          -18.982162107834164
        ],
        [
          -26.580673989363135,
          -14.715495441167498
        ],
        [
          -26.580673989363135,
          35.44049841358481
        ],
        [
          -30.847340656029814,
          35.44049841358481
        ]
      ]
    },
    {
      "position": [
        91.80770436054893,
        213.21825227206523
      ],
      "bodyType": 1,
      "angle": 0.0,
      "color": 5,
      "shapeType": 0,
      "diameter": 5.188342153598357,
      "vertices": [
        [
          -72.76225670580797,
          -1.9622129127277503
        ],
        [
          -72.76225670580797,
          1.7064990071976638
        ],
        [
          -76.43096862573339,
          1.7064990071976638
        ],
        [
          -76.43096862573339,
          -1.9622129127277503
        ]
      ]
    },
    {
      "position": [
        36.61926826281569,
        206.73793265679282
      ],
      "bodyType": 1,
      "angle": 0.0,
      "color": 2,
      "shapeType": 1,
      "diameter": 9.0,
      "radius": 4.5
    }
  ],
  "relationship": {
    "bodyId1": 9,
    "bodyId2": 6,
    "relationships": [
      0
    ]
  },
  "metadata": {
    "description": "Make sure the green ball is touching the purple poly.",
    "tier": 3
  }
}