{
  "scene_dimensions": [
    256,
    256
  ],
  "bodies": [
    {
      "position": [
        128.0,
        258.5
      ],
      "bodyType": 0,
      "angle": 0.0,
      "color": 6,
      "shapeType": 0,
      "diameter": 256.0488234692751,
      "vertices": [
        [
          128.0,
          2.5
        ],
        [
          -128.0,
          2.5
        ],
        [
          -128.0,
          -2.5
        ],
        [
          128.0,
          -2.5
        ]
      ]
    },
    {
      "position": [
        -2.5,
        128.0
      ],
      "bodyType": 0,
      "angle": 0.0,
      "color": 6,
      "shapeType": 0,
      "diameter": 256.0488234692751,
      "vertices": [
        [
          2.5,
          128.0
        ],
        [
          -2.5,
          128.0
        ],
        [
          -2.5,
          -128.0
        ],
        [
          2.5,
          -128.0
        ]
      ]
    },
    {
      "position": [
        128.0,
        -2.5
      ],
      "bodyType": 0,
      "angle": 0.0,
      "color": 6,
      "shapeType": 0,
      "diameter": 256.0488234692751,
      "vertices": [
        [
          128.0,
          2.5
        ],
        [
          -128.0,
          2.5
        ],
        [
          -128.0,
          -2.5
        ],
        [
          128.0,
          -2.5
        ]
      ]
    },
    {
      "position": [
        258.5,
        128.0
      ],
      "bodyType": 0,
      "angle": 0.0,
      "color": 6,
      "shapeType": 0,
      "diameter": 256.0488234692751,
      "vertices": [
        [
          2.5,
          128.0
        ],
        [
          -2.5,
          128.0
        ],
        [
          -2.5,
          -128.0
        ],
        [
          2.5,
          -128.0
        ]
      ]
    },
    {
      "position": [
        44.759595025850544,
        183.21254717074225
      ],
      "bodyType": 0,
      "angle": 0.0,
      "color": 6,
      "shapeType": 0,
      "diameter": 215.25512231811075,
      "vertices": [
        [
          56.93962877603519,
          -72.78745282925773
        ],
        [
          56.93962877603519,
          16.635051274679483
        ],
        [
          -44.759595025850544,
          116.92821748365758
        ],
        [
          -44.759595025850544,
          -72.78745282925773
        ]
      ]
    },
    {
      "position": [
        209.8946197919965,
        245.33333333333334
      ],
      "bodyType": 0,
      "angle": 0.0,
      "color": 4,
      "shapeType": 0,
      "diameter": 45.47801499264536,
      "vertices": [
        [
          22.63871354133684,
          -2.1333333333333346
        ],
        [
          22.63871354133684,
          2.133333333333333
        ],
        [
          -22.63871354133684,
          2.133333333333333
        ],
        [
          -22.63871354133684,
          -2.1333333333333346
        ]
      ]
    },
    {
      "position": [
        209.89461979199655,
        229.91801287683825
      ],
      "bodyType": 0,
      "angle": 0.0,
      "color": 6,
      "shapeType": 0,
      "diameter": 68.22272070705553,
      "vertices": [
        [
          -26.90538020800355,
          -26.08198712316174
        ],
        [
          -22.638713541336898,
          -21.815320456495073
        ],
        [
          -22.638713541336898,
          42.00718364744215
        ],
        [
          -26.90538020800355,
          42.00718364744215
        ]
      ]
    },
    {
      "position": [
        47.08273416286881,
        56.9828716566868
      ],
      "bodyType": 1,
      "angle": 0.0,
      "color": 2,
      "shapeType": 1,
      "diameter": 13.0,
      "radius": 6.5
    },
    {
      "position": [
        143.41089835960605,
        243.28874794803139
      ],
      "bodyType": 0,
      "angle": 0.0,
      "color": 6,
      "shapeType": 0,
      "diameter": 87.21100213018646,
      "vertices": [
        [
          41.71167455772027,
          -12.71125205196861
        ],
        [
          41.71167455772027,
          12.71125205196861
        ],
        [
          -41.711674557720315,
          12.71125205196861
        ],
        [
          -41.711674557720315,
          -12.71125205196861
        ]
      ]
    },
    {
      "position": [
        143.41089835960602,
        137.84086054346434
      ],
      "bodyType": 1,
      "angle": 0.0,
      "color": 5,
      "shapeType": 0,
      "diameter": 78.41029526855138,
      "vertices": [
        [
          38.550646946995556,
          -7.133808309273206
        ],
        [
          38.550646946995556,
          7.133808309273206
        ],
        [
          -38.55064694699554,
          7.133808309273206
        ],
        [
          -38.55064694699554,
          -7.133808309273206
        ]
      ]
    }
  ],
  "relationship": {
    "bodyId1": 7,
    "bodyId2": 5,
    "relationships": [
      0
    ]
  },
  "metadata": {
    "description": "Make sure the green ball is touching the purple poly.",
    "tier": 3
  }
}