{
  "scene_dimensions": [
    256,
    256
  ],
  "bodies": [
    {
      "position": [
        128.0,
        258.5
      ],
      "bodyType": 0,
      "angle": 0.0,
      "color": 6,
      "shapeType": 0,
      "diameter": 256.0488234692751,
      "vertices": [
        [
          128.0,
          2.5
        ],
        [
          -128.0,
          2.5
        ],
        [
          -128.0,
          -2.5
        ],
        [
          128.0,
          -2.5
        ]
      ]
    },
    {
      "position": [
        -2.5,
        128.0
      ],
      "bodyType": 0,
      "angle": 0.0,
      "color": 6,
      "shapeType": 0,
      "diameter": 256.0488234692751,
      "vertices": [
        [
          2.5,
          128.0
        ],
        [
          -2.5,
          128.0
        ],
        [
          -2.5,
          -128.0
        ],
        [
          2.5,
          -128.0
        ]
      ]
    },
    {
      "position": [
        128.0,
        -2.5
      ],
      "bodyType": 0,
      "angle": 0.0,
      "color": 6,
      "shapeType": 0,
      "diameter": 256.0488234692751,
      "vertices": [
        [
          128.0,
          2.5
        ],
        [
          -128.0,
          2.5
        ],
        [
          -128.0,
          -2.5
        ],
        [
          128.0,
          -2.5
        ]
      ]
    },
    {
      "position": [
        258.5,
        128.0
      ],
      "bodyType": 0,
      "angle": 0.0,
      "color": 6,
      "shapeType": 0,
      "diameter": 256.0488234692751,
      "vertices": [
        [
          2.5,
          128.0
        ],
        [
          -2.5,
          128.0
        ],
        [
          -2.5,
          -128.0
        ],
        [
          2.5,
          -128.0
        ]
      ]
    },
    {
      "position": [
        29.53808586501693,
        245.33333333333334
      ],
      "bodyType": 0,
      "angle": 0.0,
      "color": 4,
      "shapeType": 0,
      "diameter": 50.722607953844694,
      "vertices": [
        [
          25.27141919835026,
          -2.1333333333333346
        ],
        [
          25.27141919835026,
          2.133333333333333
        ],
        [
          -25.271419198350266,
          2.133333333333333
        ],
        [
          -25.271419198350266,
          -2.1333333333333346
        ]
      ]
    },
    {
      "position": [
        29.538085865016935,
        248.39229131384585
      ],
      "bodyType": 0,
      "angle": 0.0,
      "color": 6,
      "shapeType": 0,
      "diameter": 26.24799982394004,
      "vertices": [
        [
          -29.538085865016935,
          -7.607708686154142
        ],
        [
          -25.27141919835027,
          -3.3410420194874755
        ],
        [
          -25.27141919835027,
          18.291191875705856
        ],
        [
          -29.538085865016935,
          18.291191875705856
        ]
      ]
    },
    {
      "position": [
        83.357939209878,
        223.70109943814
      ],
      "bodyType": 1,
      "angle": 0.0,
      "color": 5,
      "shapeType": 0,
      "diameter": 30.09419474555395,
      "vertices": [
        [
          14.895100813177493,
          -2.1333333333333293
        ],
        [
          14.895100813177493,
          2.133333333333333
        ],
        [
          -14.895100813177478,
          2.133333333333333
        ],
        [
          -14.895100813177478,
          -2.1333333333333293
        ]
      ]
    },
    {
      "position": [
        128.42277884655584,
        223.70109943814
      ],
      "bodyType": 1,
      "angle": 0.0,
      "color": 5,
      "shapeType": 0,
      "diameter": 58.787847110606315,
      "vertices": [
        [
          29.316405490167,
          -2.1333333333333293
        ],
        [
          29.316405490167,
          2.133333333333333
        ],
        [
          -29.31640549016703,
          2.133333333333333
        ],
        [
          -29.31640549016703,
          -2.1333333333333293
        ]
      ]
    },
    {
      "position": [
        67.60950506336718,
        245.18388305240333
      ],
      "bodyType": 0,
      "angle": 0.0,
      "color": 6,
      "shapeType": 0,
      "diameter": 27.554031545446527,
      "vertices": [
        [
          8.533333333333346,
          -10.816116947596665
        ],
        [
          8.533333333333346,
          10.816116947596665
        ],
        [
          -8.533333333333324,
          10.816116947596665
        ],
        [
          -8.533333333333324,
          -10.816116947596665
        ]
      ]
    },
    {
      "position": [
        63.34283839670053,
        232.23443277147334
      ],
      "bodyType": 0,
      "angle": 0.0,
      "color": 6,
      "shapeType": 0,
      "diameter": 9.540556703999107,
      "vertices": [
        [
          4.266666666666666,
          -2.133333333333333
        ],
        [
          4.266666666666666,
          2.133333333333333
        ],
        [
          -4.266666666666673,
          2.133333333333333
        ],
        [
          -4.266666666666673,
          -2.133333333333333
        ]
      ]
    },
    {
      "position": [
        196.20292550169478,
        245.18388305240333
      ],
      "bodyType": 0,
      "angle": 0.0,
      "color": 6,
      "shapeType": 0,
      "diameter": 121.53482635656258,
      "vertices": [
        [
          59.79707449830522,
          -10.816116947596665
        ],
        [
          59.79707449830522,
          10.816116947596665
        ],
        [
          -59.79707449830525,
          10.816116947596665
        ],
        [
          -59.79707449830525,
          -10.816116947596665
        ]
      ]
    },
    {
      "position": [
        163.3974943177297,
        243.05054971907
      ],
      "bodyType": 0,
      "angle": 0.0,
      "color": 6,
      "shapeType": 0,
      "diameter": 28.263385106489945,
      "vertices": [
        [
          5.658309981006795,
          -12.949450280930002
        ],
        [
          5.658309981006795,
          12.949450280929995
        ],
        [
          -5.658309981006852,
          12.949450280929995
        ],
        [
          -5.658309981006852,
          -12.949450280930002
        ]
      ]
    },
    {
      "position": [
        225.68910695572959,
        204.7219920794356
      ],
      "bodyType": 0,
      "angle": 0.0,
      "color": 6,
      "shapeType": 0,
      "diameter": 124.23511359104202,
      "vertices": [
        [
          30.310893044270415,
          -29.645774025371047
        ],
        [
          30.310893044270415,
          59.09581871917861
        ],
        [
          -56.633302656993095,
          -25.37910735870438
        ],
        [
          -56.633302656993095,
          -29.645774025371047
        ]
      ]
    },
    {
      "position": [
        220.2086463120765,
        60.04099395888832
      ],
      "bodyType": 1,
      "angle": 0.0,
      "color": 2,
      "shapeType": 1,
      "diameter": 13.0,
      "radius": 6.5
    }
  ],
  "relationship": {
    "bodyId1": 13,
    "bodyId2": 4,
    "relationships": [
      0
    ]
  },
  "metadata": {
    "description": "Make sure the green ball is touching the purple poly.",
    "tier": 3
  }
}