{
  "scene_dimensions": [
    256,
    256
  ],
  "bodies": [
    {
      "position": [
        128.0,
        258.5
      ],
      "bodyType": 0,
      "angle": 0.0,
      "color": 6,
      "shapeType": 0,
      "diameter": 256.0488234692751,
      "vertices": [
        [
          128.0,
          2.5
        ],
        [
          -128.0,
          2.5
        ],
        [
          -128.0,
          -2.5
        ],
        [
          128.0,
          -2.5
        ]
      ]
    },
    {
      "position": [
        -2.5,
        128.0
      ],
      "bodyType": 0,
      "angle": 0.0,
      "color": 6,
      "shapeType": 0,
      "diameter": 256.0488234692751,
      "vertices": [
        [
          2.5,
          128.0
        ],
        [
          -2.5,
          128.0
        ],
        [
          -2.5,
          -128.0
        ],
        [
          2.5,
          -128.0
        ]
      ]
    },
    {
      "position": [
        128.0,
        -2.5
      ],
      "bodyType": 0,
      "angle": 0.0,
      "color": 6,
      "shapeType": 0,
      "diameter": 256.0488234692751,
      "vertices": [
        [
          128.0,
          2.5
        ],
        [
          -128.0,
          2.5
        ],
        [
          -128.0,
          -2.5
        ],
        [
          128.0,
          -2.5
        ]
      ]
    },
    {
      "position": [
        258.5,
        128.0
      ],
      "bodyType": 0,
      "angle": 0.0,
      "color": 6,
      "shapeType": 0,
      "diameter": 256.0488234692751,
      "vertices": [
        [
          2.5,
          128.0
        ],
        [
          -2.5,
          128.0
        ],
        [
          -2.5,
          -128.0
        ],
        [
          2.5,
          -128.0
        ]
      ]
    },
    {
      "position": [
        210.54013816916688,
        193.65028084833799
      ],
      "bodyType": 0,
      "angle": 0.0,
      "color": 6,
      "shapeType": 0,
      "diameter": 185.51672027425712,
      "vertices": [
        [
          45.45986183083312,
          -62.34971915166202
        ],
        [
          45.45986183083312,
          93.62137232184921
        ],
        [
          -54.98650259256732,
          24.52472873450896
        ],
        [
          -54.98650259256732,
          -62.34971915166202
        ]
      ]
    },
    {
      "position": [
        54.9311656467863,
        245.33333333333334
      ],
      "bodyType": 0,
      "angle": 0.0,
      "color": 4,
      "shapeType": 0,
      "diameter": 63.07347484263287,
      "vertices": [
        [
          31.46449898011963,
          -2.1333333333333346
        ],
        [
          31.46449898011963,
          2.133333333333333
        ],
        [
          -31.464498980119632,
          2.133333333333333
        ],
        [
          -31.464498980119632,
          -2.1333333333333346
        ]
      ]
    },
    {
      "position": [
        54.93116564678632,
        233.16685630618173
      ],
      "bodyType": 0,
      "angle": 0.0,
      "color": 6,
      "shapeType": 0,
      "diameter": 65.67984577686394,
      "vertices": [
        [
          -35.73116564678632,
          -22.83314369381827
        ],
        [
          -31.464498980119654,
          -18.566477027151603
        ],
        [
          -31.464498980119654,
          42.70797085901938
        ],
        [
          -35.73116564678632,
          42.70797085901938
        ]
      ]
    },
    {
      "position": [
        212.10453633683272,
        69.89700092837828
      ],
      "bodyType": 1,
      "angle": 0.0,
      "color": 2,
      "shapeType": 1,
      "diameter": 13.0,
      "radius": 6.5
    },
    {
      "position": [
        122.04131676841942,
        244.56277605691452
      ],
      "bodyType": 0,
      "angle": 0.0,
      "color": 6,
      "shapeType": 0,
      "diameter": 70.82049430568507,
      "vertices": [
        [
          33.51231880818014,
          -11.437223943085495
        ],
        [
          33.51231880818014,
          11.437223943085495
        ],
        [
          -33.512318808180154,
          11.437223943085495
        ],
        [
          -33.512318808180154,
          -11.437223943085495
        ]
      ]
    },
    {
      "position": [
        122.04131676841939,
        140.61269650665884
      ],
      "bodyType": 1,
      "angle": 0.0,
      "color": 5,
      "shapeType": 0,
      "diameter": 58.6202365250301,
      "vertices": [
        [
          28.91240905056341,
          -4.812030284143887
        ],
        [
          28.91240905056341,
          4.8120302841439155
        ],
        [
          -28.912409050563383,
          4.8120302841439155
        ],
        [
          -28.912409050563383,
          -4.812030284143887
        ]
      ]
    }
  ],
  "relationship": {
    "bodyId1": 7,
    "bodyId2": 5,
    "relationships": [
      0
    ]
  },
  "metadata": {
    "description": "Make sure the green ball is touching the purple poly.",
    "tier": 3
  }
}