{
  "scene_dimensions": [
    256,
    256
  ],
  "bodies": [
    {
      "position": [
        128.0,
        258.5
      ],
      "bodyType": 0,
      "angle": 0.0,
      "color": 6,
      "shapeType": 0,
      "diameter": 256.0488234692751,
      "vertices": [
        [
          128.0,
          2.5
        ],
        [
          -128.0,
          2.5
        ],
        [
          -128.0,
          -2.5
        ],
        [
          128.0,
          -2.5
        ]
      ]
    },
    {
      "position": [
        -2.5,
        128.0
      ],
      "bodyType": 0,
      "angle": 0.0,
      "color": 6,
      "shapeType": 0,
      "diameter": 256.0488234692751,
      "vertices": [
        [
          2.5,
          128.0
        ],
        [
          -2.5,
          128.0
        ],
        [
          -2.5,
          -128.0
        ],
        [
          2.5,
          -128.0
        ]
      ]
    },
    {
      "position": [
        128.0,
        -2.5
      ],
      "bodyType": 0,
      "angle": 0.0,
      "color": 6,
      "shapeType": 0,
      "diameter": 256.0488234692751,
      "vertices": [
        [
          128.0,
          2.5
        ],
        [
          -128.0,
          2.5
        ],
        [
          -128.0,
          -2.5
        ],
        [
          128.0,
          -2.5
        ]
      ]
    },
    {
      "position": [
        258.5,
        128.0
      ],
      "bodyType": 0,
      "angle": 0.0,
      "color": 6,
      "shapeType": 0,
      "diameter": 256.0488234692751,
      "vertices": [
        [
          2.5,
          128.0
        ],
        [
          -2.5,
          128.0
        ],
        [
          -2.5,
          -128.0
        ],
        [
          2.5,
          -128.0
        ]
      ]
    },
    {
      "position": [
        182.40052435091638,
        208.36645527488807
      ],
      "bodyType": 0,
      "angle": 0.0,
      "color": 6,
      "shapeType": 0,
      "diameter": 175.33781564624667,
      "vertices": [
        [
          73.59947564908362,
          -47.63354472511194
        ],
        [
          73.59947564908362,
          47.63354472511195
        ],
        [
          -73.59947564908366,
          47.63354472511195
        ],
        [
          -73.59947564908366,
          -47.63354472511194
        ]
      ]
    },
    {
      "position": [
        221.9667857592259,
        135.08633742217629
      ],
      "bodyType": 0,
      "angle": 0.0,
      "color": 6,
      "shapeType": 0,
      "diameter": 23.30765333380951,
      "vertices": [
        [
          11.205876850218374,
          -3.1999999999999886
        ],
        [
          11.205876850218374,
          3.200000000000017
        ],
        [
          -11.205876850218402,
          3.200000000000017
        ],
        [
          -11.205876850218402,
          -3.1999999999999886
        ]
      ]
    },
    {
      "position": [
        249.626193417404,
        155.7831229340673
      ],
      "bodyType": 0,
      "angle": 0.0,
      "color": 6,
      "shapeType": 0,
      "diameter": 24.210168734164384,
      "vertices": [
        [
          6.373806582595989,
          -4.949787615708786
        ],
        [
          6.373806582595989,
          9.899575231417558
        ],
        [
          -12.74761316519195,
          -4.949787615708786
        ]
      ]
    },
    {
      "position": [
        226.0781804941885,
        154.2329105497761
      ],
      "bodyType": 1,
      "angle": 0.0,
      "color": 2,
      "shapeType": 1,
      "diameter": 13.0,
      "radius": 6.5
    },
    {
      "position": [
        57.38386393382413,
        245.33333333333334
      ],
      "bodyType": 0,
      "angle": 0.0,
      "color": 4,
      "shapeType": 0,
      "diameter": 89.00765603379708,
      "vertices": [
        [
          44.452666928392176,
          -2.1333333333333346
        ],
        [
          44.452666928392176,
          2.133333333333333
        ],
        [
          -44.45266692839219,
          2.133333333333333
        ],
        [
          -44.45266692839219,
          -2.1333333333333346
        ]
      ]
    },
    {
      "position": [
        57.38386393382419,
        243.0666606981661
      ],
      "bodyType": 0,
      "angle": 0.0,
      "color": 6,
      "shapeType": 0,
      "diameter": 46.70614368020698,
      "vertices": [
        [
          -48.71933359505891,
          -12.933339301833914
        ],
        [
          -44.45266692839225,
          -8.666672635167249
        ],
        [
          -44.45266692839225,
          33.57751333528395
        ],
        [
          -48.71933359505891,
          33.57751333528395
        ]
      ]
    }
  ],
  "relationship": {
    "bodyId1": 7,
    "bodyId2": 8,
    "relationships": [
      0
    ]
  },
  "metadata": {
    "description": "Make sure the green ball is touching the purple poly.",
    "tier": 3
  }
}