{
  "scene_dimensions": [
    256,
    256
  ],
  "bodies": [
    {
      "position": [
        128.0,
        258.5
      ],
      "bodyType": 0,
      "angle": 0.0,
      "color": 6,
      "shapeType": 0,
      "diameter": 256.0488234692751,
      "vertices": [
        [
          128.0,
          2.5
        ],
        [
          -128.0,
          2.5
        ],
        [
          -128.0,
          -2.5
        ],
        [
          128.0,
          -2.5
        ]
      ]
    },
    {
      "position": [
        -2.5,
        128.0
      ],
      "bodyType": 0,
      "angle": 0.0,
      "color": 6,
      "shapeType": 0,
      "diameter": 256.0488234692751,
      "vertices": [
        [
          2.5,
          128.0
        ],
        [
          -2.5,
          128.0
        ],
        [
          -2.5,
          -128.0
        ],
        [
          2.5,
          -128.0
        ]
      ]
    },
    {
      "position": [
        128.0,
        -2.5
      ],
      "bodyType": 0,
      "angle": 0.0,
      "color": 6,
      "shapeType": 0,
      "diameter": 256.0488234692751,
      "vertices": [
        [
          128.0,
          2.5
        ],
        [
          -128.0,
          2.5
        ],
        [
          -128.0,
          -2.5
        ],
        [
          128.0,
          -2.5
        ]
      ]
    },
    {
      "position": [
        258.5,
        128.0
      ],
      "bodyType": 0,
      "angle": 0.0,
      "color": 6,
      "shapeType": 0,
      "diameter": 256.0488234692751,
      "vertices": [
        [
          2.5,
          128.0
        ],
        [
          -2.5,
          128.0
        ],
        [
          -2.5,
          -128.0
        ],
        [
          2.5,
          -128.0
        ]
      ]
    },
    {
      "position": [
        84.87999510296139,
        215.9786243089005
      ],
      "bodyType": 0,
      "angle": 0.0,
      "color": 6,
      "shapeType": 0,
      "diameter": 187.68403321419623,
      "vertices": [
        [
          84.87999510296139,
          -40.02137569109951
        ],
        [
          84.87999510296139,
          40.02137569109951
        ],
        [
          -84.87999510296139,
          40.02137569109951
        ],
        [
          -84.87999510296139,
          -40.02137569109951
        ]
      ]
    },
    {
      "position": [
        95.69248005921618,
        147.83481423709182
      ],
      "bodyType": 0,
      "angle": 0.0,
      "color": 6,
      "shapeType": 0,
      "diameter": 40.711948448741126,
      "vertices": [
        [
          20.10287757071707,
          -3.200000000000003
        ],
        [
          20.10287757071707,
          3.1999999999999886
        ],
        [
          -20.10287757071704,
          3.1999999999999886
        ],
        [
          -20.10287757071704,
          -3.200000000000003
        ]
      ]
    },
    {
      "position": [
        1.7252204280256616,
        172.26445019260933
      ],
      "bodyType": 0,
      "angle": 0.0,
      "color": 6,
      "shapeType": 0,
      "diameter": 12.227768055102151,
      "vertices": [
        [
          3.4504408560513236,
          -3.6927984251916683
        ],
        [
          -1.7252204280256616,
          7.385596850383365
        ],
        [
          -1.7252204280256616,
          -3.6927984251916683
        ]
      ]
    },
    {
      "position": [
        102.39489398406353,
        166.45724861780099
      ],
      "bodyType": 1,
      "angle": 0.0,
      "color": 2,
      "shapeType": 1,
      "diameter": 19.0,
      "radius": 9.5
    },
    {
      "position": [
        195.17592066600156,
        245.33333333333334
      ],
      "bodyType": 0,
      "angle": 0.0,
      "color": 4,
      "shapeType": 0,
      "diameter": 34.28582730264515,
      "vertices": [
        [
          17.009655415251387,
          -2.1333333333333346
        ],
        [
          17.009655415251387,
          2.133333333333333
        ],
        [
          -17.009655415251387,
          2.133333333333333
        ],
        [
          -17.009655415251387,
          -2.1333333333333346
        ]
      ]
    },
    {
      "position": [
        195.17592066600156,
        242.89083084906397
      ],
      "bodyType": 0,
      "angle": 0.0,
      "color": 6,
      "shapeType": 0,
      "diameter": 36.70836220447178,
      "vertices": [
        [
          -21.276322081918067,
          -13.109169150936022
        ],
        [
          -17.009655415251387,
          -8.842502484269357
        ],
        [
          -17.009655415251387,
          23.350389421408867
        ],
        [
          -21.276322081918067,
          23.350389421408867
        ]
      ]
    }
  ],
  "relationship": {
    "bodyId1": 7,
    "bodyId2": 8,
    "relationships": [
      0
    ]
  },
  "metadata": {
    "description": "Make sure the green ball is touching the purple poly.",
    "tier": 3
  }
}