{
  "scene_dimensions": [
    256,
    256
  ],
  "bodies": [
    {
      "position": [
        128.0,
        258.5
      ],
      "bodyType": 0,
      "angle": 0.0,
      "color": 6,
      "shapeType": 0,
      "diameter": 256.0488234692751,
      "vertices": [
        [
          128.0,
          2.5
        ],
        [
          -128.0,
          2.5
        ],
        [
          -128.0,
          -2.5
        ],
        [
          128.0,
          -2.5
        ]
      ]
    },
    {
      "position": [
        -2.5,
        128.0
      ],
      "bodyType": 0,
      "angle": 0.0,
      "color": 6,
      "shapeType": 0,
      "diameter": 256.0488234692751,
      "vertices": [
        [
          2.5,
          128.0
        ],
        [
          -2.5,
          128.0
        ],
        [
          -2.5,
          -128.0
        ],
        [
          2.5,
          -128.0
        ]
      ]
    },
    {
      "position": [
        128.0,
        -2.5
      ],
      "bodyType": 0,
      "angle": 0.0,
      "color": 6,
      "shapeType": 0,
      "diameter": 256.0488234692751,
      "vertices": [
        [
          128.0,
          2.5
        ],
        [
          -128.0,
          2.5
        ],
        [
          -128.0,
          -2.5
        ],
        [
          128.0,
          -2.5
        ]
      ]
    },
    {
      "position": [
        258.5,
        128.0
      ],
      "bodyType": 0,
      "angle": 0.0,
      "color": 6,
      "shapeType": 0,
      "diameter": 256.0488234692751,
      "vertices": [
        [
          2.5,
          128.0
        ],
        [
          -2.5,
          128.0
        ],
        [
          -2.5,
          -128.0
        ],
        [
          2.5,
          -128.0
        ]
      ]
    },
    {
      "position": [
        53.98434690100538,
        214.92114571069607
      ],
      "bodyType": 0,
      "angle": 0.0,
      "color": 6,
      "shapeType": 0,
      "diameter": 151.36896298564207,
      "vertices": [
        [
          61.8136674721199,
          -41.078854289303926
        ],
        [
          61.8136674721199,
          23.52831583911584
        ],
        [
          -53.98434690100538,
          56.4064411279545
        ],
        [
          -53.98434690100538,
          -41.078854289303926
        ]
      ]
    },
    {
      "position": [
        233.84840551127132,
        239.4671418244185
      ],
      "bodyType": 0,
      "angle": 0.0,
      "color": 6,
      "shapeType": 0,
      "diameter": 44.81496578113023,
      "vertices": [
        [
          -22.151594488728648,
          -16.53285817558152
        ],
        [
          -17.884927822061968,
          -12.266191508914854
        ],
        [
          -17.884927822061968,
          28.078538501942813
        ],
        [
          -22.151594488728648,
          28.078538501942813
        ]
      ]
    },
    {
      "position": [
        12.8,
        152.11470458274158
      ],
      "bodyType": 1,
      "angle": 0.0,
      "color": 2,
      "shapeType": 1,
      "diameter": 13.0,
      "radius": 6.5
    },
    {
      "position": [
        165.2407460311673,
        189.2594965382469
      ],
      "bodyType": 1,
      "angle": 0.0,
      "color": 5,
      "shapeType": 0,
      "diameter": 86.19113317963338,
      "vertices": [
        [
          43.042731658042044,
          -2.1333333333333258
        ],
        [
          43.042731658042044,
          2.13333333333334
        ],
        [
          -43.042731658042015,
          2.13333333333334
        ],
        [
          -43.042731658042015,
          -2.1333333333333258
        ]
      ]
    },
    {
      "position": [
        143.84614123034444,
        239.8226534373141
      ],
      "bodyType": 1,
      "angle": 0.0,
      "color": 5,
      "shapeType": 0,
      "diameter": 31.392052616859512,
      "vertices": [
        [
          8.507126762642798,
          -13.190679896019232
        ],
        [
          8.507126762642798,
          13.190679896019237
        ],
        [
          -8.50712676264277,
          13.190679896019237
        ],
        [
          -8.50712676264277,
          -13.190679896019232
        ]
      ]
    },
    {
      "position": [
        184.83234051989598,
        254.50666666666666
      ],
      "bodyType": 0,
      "angle": 0.0,
      "color": 4,
      "shapeType": 0,
      "diameter": 138.10095192985676,
      "vertices": [
        [
          69.0343261467707,
          -1.4933333333333334
        ],
        [
          69.0343261467707,
          1.4933333333333334
        ],
        [
          -69.0343261467707,
          1.4933333333333334
        ],
        [
          -69.0343261467707,
          -1.4933333333333334
        ]
      ]
    }
  ],
  "relationship": {
    "bodyId1": 6,
    "bodyId2": 9,
    "relationships": [
      0
    ]
  },
  "metadata": {
    "description": "Make sure the green ball is touching the purple poly.",
    "tier": 3
  }
}