{
  "scene_dimensions": [
    256,
    256
  ],
  "bodies": [
    {
      "position": [
        128.0,
        258.5
      ],
      "bodyType": 0,
      "angle": 0.0,
      "color": 6,
      "shapeType": 0,
      "diameter": 256.0488234692751,
      "vertices": [
        [
          128.0,
          2.5
        ],
        [
          -128.0,
          2.5
        ],
        [
          -128.0,
          -2.5
        ],
        [
          128.0,
          -2.5
        ]
      ]
    },
    {
      "position": [
        -2.5,
        128.0
      ],
      "bodyType": 0,
      "angle": 0.0,
      "color": 6,
      "shapeType": 0,
      "diameter": 256.0488234692751,
      "vertices": [
        [
          2.5,
          128.0
        ],
        [
          -2.5,
          128.0
        ],
        [
          -2.5,
          -128.0
        ],
        [
          2.5,
          -128.0
        ]
      ]
    },
    {
      "position": [
        128.0,
        -2.5
      ],
      "bodyType": 0,
      "angle": 0.0,
      "color": 6,
      "shapeType": 0,
      "diameter": 256.0488234692751,
      "vertices": [
        [
          128.0,
          2.5
        ],
        [
          -128.0,
          2.5
        ],
        [
          -128.0,
          -2.5
        ],
        [
          128.0,
          -2.5
        ]
      ]
    },
    {
      "position": [
        258.5,
        128.0
      ],
      "bodyType": 0,
      "angle": 0.0,
      "color": 6,
      "shapeType": 0,
      "diameter": 256.0488234692751,
      "vertices": [
        [
          2.5,
          128.0
        ],
        [
          -2.5,
          128.0
        ],
        [
          -2.5,
          -128.0
        ],
        [
          2.5,
          -128.0
        ]
      ]
    },
    {
      "position": [
        211.16102389534655,
        215.77127181002732
      ],
      "bodyType": 0,
      "angle": 0.0,
      "color": 6,
      "shapeType": 0,
      "diameter": 141.96688014175143,
      "vertices": [
        [
          44.838976104653455,
          -40.228728189972685
        ],
        [
          44.838976104653455,
          61.05731480453424
        ],
        [
          -54.63832055994891,
          14.848153272273613
        ],
        [
          -54.63832055994891,
          -40.228728189972685
        ]
      ]
    },
    {
      "position": [
        23.013925786221552,
        245.33333333333334
      ],
      "bodyType": 0,
      "angle": 0.0,
      "color": 4,
      "shapeType": 0,
      "diameter": 37.736498809870795,
      "vertices": [
        [
          18.747259119554887,
          -2.1333333333333346
        ],
        [
          18.747259119554887,
          2.133333333333333
        ],
        [
          -18.747259119554887,
          2.133333333333333
        ],
        [
          -18.747259119554887,
          -2.1333333333333346
        ]
      ]
    },
    {
      "position": [
        23.013925786221535,
        240.68436767840876
      ],
      "bodyType": 0,
      "angle": 0.0,
      "color": 6,
      "shapeType": 0,
      "diameter": 42.52710584929579,
      "vertices": [
        [
          -23.013925786221535,
          -15.315632321591252
        ],
        [
          -18.74725911955487,
          -11.048965654924586
        ],
        [
          -18.74725911955487,
          26.99689877113309
        ],
        [
          -23.013925786221535,
          26.99689877113309
        ]
      ]
    },
    {
      "position": [
        243.2,
        148.31395700549308
      ],
      "bodyType": 1,
      "angle": 0.0,
      "color": 2,
      "shapeType": 1,
      "diameter": 13.0,
      "radius": 6.5
    },
    {
      "position": [
        99.78194412058703,
        198.78978520442038
      ],
      "bodyType": 1,
      "angle": 0.0,
      "color": 5,
      "shapeType": 0,
      "diameter": 100.77188396442033,
      "vertices": [
        [
          50.3407592148106,
          -2.1333333333333258
        ],
        [
          50.3407592148106,
          2.13333333333334
        ],
        [
          -50.34075921481059,
          2.13333333333334
        ],
        [
          -50.34075921481059,
          -2.1333333333333258
        ]
      ]
    },
    {
      "position": [
        144.78185321936485,
        241.06526393525084
      ],
      "bodyType": 1,
      "angle": 0.0,
      "color": 5,
      "shapeType": 0,
      "diameter": 30.571274707361717,
      "vertices": [
        [
          3.256434858019418,
          -14.93473606474917
        ],
        [
          3.256434858019418,
          14.93473606474917
        ],
        [
          -3.256434858019446,
          14.93473606474917
        ],
        [
          -3.256434858019446,
          -14.93473606474917
        ]
      ]
    }
  ],
  "relationship": {
    "bodyId1": 7,
    "bodyId2": 5,
    "relationships": [
      0
    ]
  },
  "metadata": {
    "description": "Make sure the green ball is touching the purple poly.",
    "tier": 3
  }
}