{
  "scene_dimensions": [
    256,
    256
  ],
  "bodies": [
    {
      "position": [
        128.0,
        258.5
      ],
      "bodyType": 0,
      "angle": 0.0,
      "color": 6,
      "shapeType": 0,
      "diameter": 256.0488234692751,
      "vertices": [
        [
          128.0,
          2.5
        ],
        [
          -128.0,
          2.5
        ],
        [
          -128.0,
          -2.5
        ],
        [
          128.0,
          -2.5
        ]
      ]
    },
    {
      "position": [
        -2.5,
        128.0
      ],
      "bodyType": 0,
      "angle": 0.0,
      "color": 6,
      "shapeType": 0,
      "diameter": 256.0488234692751,
      "vertices": [
        [
          2.5,
          128.0
        ],
        [
          -2.5,
          128.0
        ],
        [
          -2.5,
          -128.0
        ],
        [
          2.5,
          -128.0
        ]
      ]
    },
    {
      "position": [
        128.0,
        -2.5
      ],
      "bodyType": 0,
      "angle": 0.0,
      "color": 6,
      "shapeType": 0,
      "diameter": 256.0488234692751,
      "vertices": [
        [
          128.0,
          2.5
        ],
        [
          -128.0,
          2.5
        ],
        [
          -128.0,
          -2.5
        ],
        [
          128.0,
          -2.5
        ]
      ]
    },
    {
      "position": [
        258.5,
        128.0
      ],
      "bodyType": 0,
      "angle": 0.0,
      "color": 6,
      "shapeType": 0,
      "diameter": 256.0488234692751,
      "vertices": [
        [
          2.5,
          128.0
        ],
        [
          -2.5,
          128.0
        ],
        [
          -2.5,
          -128.0
        ],
        [
          2.5,
          -128.0
        ]
      ]
    },
    {
      "position": [
        50.16855791718828,
        210.27519425747852
      ],
      "bodyType": 0,
      "angle": 0.0,
      "color": 6,
      "shapeType": 0,
      "diameter": 154.0284331135609,
      "vertices": [
        [
          58.022842330896054,
          -45.72480574252148
        ],
        [
          58.022842330896054,
          24.694746106174904
        ],
        [
          -50.16855791718828,
          63.908123251360294
        ],
        [
          -50.16855791718828,
          -45.72480574252148
        ]
      ]
    },
    {
      "position": [
        234.5401277368589,
        238.7958825662536
      ],
      "bodyType": 0,
      "angle": 0.0,
      "color": 6,
      "shapeType": 0,
      "diameter": 45.93708942538145,
      "vertices": [
        [
          -21.459872263141193,
          -17.204117433746415
        ],
        [
          -17.19320559647454,
          -12.93745076707975
        ],
        [
          -17.19320559647454,
          28.53439741349199
        ],
        [
          -21.459872263141193,
          28.53439741349199
        ]
      ]
    },
    {
      "position": [
        12.8,
        139.96707100611823
      ],
      "bodyType": 1,
      "angle": 0.0,
      "color": 2,
      "shapeType": 1,
      "diameter": 13.0,
      "radius": 6.5
    },
    {
      "position": [
        162.12916119423437,
        183.44711481797026
      ],
      "bodyType": 1,
      "angle": 0.0,
      "color": 5,
      "shapeType": 0,
      "diameter": 95.17121049738553,
      "vertices": [
        [
          47.53776094615,
          -2.13333333333334
        ],
        [
          47.53776094615,
          2.1333333333333258
        ],
        [
          -47.53776094615003,
          2.1333333333333258
        ],
        [
          -47.53776094615003,
          -2.13333333333334
        ]
      ]
    },
    {
      "position": [
        128.88328343746724,
        235.14461133560252
      ],
      "bodyType": 1,
      "angle": 0.0,
      "color": 5,
      "shapeType": 0,
      "diameter": 39.07732502965935,
      "vertices": [
        [
          7.903676804894104,
          -17.86872199773082
        ],
        [
          7.903676804894104,
          17.868721997730823
        ],
        [
          -7.903676804894076,
          17.868721997730823
        ],
        [
          -7.903676804894076,
          -17.86872199773082
        ]
      ]
    },
    {
      "position": [
        181.0290334573755,
        254.50666666666666
      ],
      "bodyType": 0,
      "angle": 0.0,
      "color": 4,
      "shapeType": 0,
      "diameter": 145.70587985356912,
      "vertices": [
        [
          72.83763320929117,
          -1.4933333333333334
        ],
        [
          72.83763320929117,
          1.4933333333333334
        ],
        [
          -72.83763320929117,
          1.4933333333333334
        ],
        [
          -72.83763320929117,
          -1.4933333333333334
        ]
      ]
    }
  ],
  "relationship": {
    "bodyId1": 6,
    "bodyId2": 9,
    "relationships": [
      0
    ]
  },
  "metadata": {
    "description": "Make sure the green ball is touching the purple poly.",
    "tier": 3
  }
}